[{"title":"Refactor Frontend Components","description":"Implement user authentication feature","jobType":"OTHER","jobState":"NEW","earnings":481.5,"companyId":"89","freelancerId":null},
{"title":"Integrate Third-Party API","description":"Write unit tests for new functionality","jobType":"REVIEW","jobState":"NEW","earnings":947.8,"companyId":"87","freelancerId":null},
{"title":"Write Unit Tests","description":"Optimize database queries for performance","jobType":"REVIEW","jobState":"NEW","earnings":676.2,"companyId":"51","freelancerId":null},
{"title":"Implement User Authentication","description":"Optimize database queries for performance","jobType":"OTHER","jobState":"NEW","earnings":482.4,"companyId":"54","freelancerId":null},
{"title":"Optimize Database Queries","description":"Optimize database queries for performance","jobType":"OTHER","jobState":"NEW","earnings":718.7,"companyId":"59","freelancerId":null},
{"title":"Implement User Authentication","description":"Fix bug causing application crash","jobType":"REVIEW","jobState":"NEW","earnings":375.5,"companyId":"27","freelancerId":null},
{"title":"Refactor Frontend Components","description":"Optimize database queries for performance","jobType":"REVIEW","jobState":"NEW","earnings":478.6,"companyId":"18","freelancerId":null},
{"title":"Write Unit Tests","description":"Fix bug causing application crash","jobType":"OTHER","jobState":"NEW","earnings":208.8,"companyId":"69","freelancerId":null},
{"title":"Write Unit Tests","description":"Fix bug causing application crash","jobType":"TEST","jobState":"NEW","earnings":238.8,"companyId":"26","freelancerId":null},
{"title":"Write Unit Tests","description":"Optimize database queries for performance","jobType":"OTHER","jobState":"NEW","earnings":201.8,"companyId":"38","freelancerId":null},
{"title":"Refactor Frontend Components","description":"Optimize database queries for performance","jobType":"IMPLEMENT","jobState":"NEW","earnings":176.6,"companyId":"94","freelancerId":null},
{"title":"Write Unit Tests","description":"Refactor code to improve readability","jobType":"IMPLEMENT","jobState":"NEW","earnings":986.6,"companyId":"22","freelancerId":null},
{"title":"Refactor Frontend Components","description":"Implement user authentication feature","jobType":"OTHER","jobState":"NEW","earnings":333.1,"companyId":"30","freelancerId":null},
{"title":"Refactor Frontend Components","description":"Write unit tests for new functionality","jobType":"TEST","jobState":"NEW","earnings":177.6,"companyId":"3","freelancerId":null},
{"title":"Write Unit Tests","description":"Write unit tests for new functionality","jobType":"REVIEW","jobState":"NEW","earnings":934.9,"companyId":"14","freelancerId":null},
{"title":"Integrate Third-Party API","description":"Fix bug causing application crash","jobType":"REVIEW","jobState":"NEW","earnings":653.5,"companyId":"88","freelancerId":null},
{"title":"Optimize Database Queries","description":"Refactor code to improve readability","jobType":"REVIEW","jobState":"NEW","earnings":910.2,"companyId":"52","freelancerId":null},
{"title":"Optimize Database Queries","description":"Fix bug causing application crash","jobType":"TEST","jobState":"NEW","earnings":835.7,"companyId":"88","freelancerId":null},
{"title":"Refactor Frontend Components","description":"Optimize database queries for performance","jobType":"IMPLEMENT","jobState":"NEW","earnings":961.1,"companyId":"57","freelancerId":null},
{"title":"Write Unit Tests","description":"Write unit tests for new functionality","jobType":"OTHER","jobState":"NEW","earnings":248.6,"companyId":"15","freelancerId":null},
{"title":"Write Unit Tests","description":"Refactor code to improve readability","jobType":"TEST","jobState":"NEW","earnings":878.0,"companyId":"71","freelancerId":null},
{"title":"Integrate Third-Party API","description":"Refactor code to improve readability","jobType":"TEST","jobState":"NEW","earnings":371.1,"companyId":"75","freelancerId":null},
{"title":"Optimize Database Queries","description":"Implement user authentication feature","jobType":"TEST","jobState":"NEW","earnings":866.7,"companyId":"99","freelancerId":null},
{"title":"Optimize Database Queries","description":"Optimize database queries for performance","jobType":"REVIEW","jobState":"NEW","earnings":104.8,"companyId":"14","freelancerId":null},
{"title":"Implement User Authentication","description":"Optimize database queries for performance","jobType":"TEST","jobState":"NEW","earnings":424.2,"companyId":"36","freelancerId":null},
{"title":"Integrate Third-Party API","description":"Implement user authentication feature","jobType":"OTHER","jobState":"NEW","earnings":999.0,"companyId":"86","freelancerId":null},
{"title":"Integrate Third-Party API","description":"Refactor code to improve readability","jobType":"REVIEW","jobState":"NEW","earnings":149.1,"companyId":"65","freelancerId":null},
{"title":"Implement User Authentication","description":"Implement user authentication feature","jobType":"IMPLEMENT","jobState":"NEW","earnings":419.3,"companyId":"98","freelancerId":null},
{"title":"Write Unit Tests","description":"Fix bug causing application crash","jobType":"OTHER","jobState":"NEW","earnings":682.5,"companyId":"54","freelancerId":null},
{"title":"Integrate Third-Party API","description":"Implement user authentication feature","jobType":"TEST","jobState":"NEW","earnings":166.4,"companyId":"53","freelancerId":null},
{"title":"Implement User Authentication","description":"Optimize database queries for performance","jobType":"REVIEW","jobState":"NEW","earnings":899.2,"companyId":"2","freelancerId":null},
{"title":"Integrate Third-Party API","description":"Implement user authentication feature","jobType":"OTHER","jobState":"NEW","earnings":284.2,"companyId":"39","freelancerId":null},
{"title":"Implement User Authentication","description":"Optimize database queries for performance","jobType":"OTHER","jobState":"NEW","earnings":826.8,"companyId":"4","freelancerId":null},
{"title":"Implement User Authentication","description":"Refactor code to improve readability","jobType":"TEST","jobState":"NEW","earnings":853.2,"companyId":"45","freelancerId":null},
{"title":"Implement User Authentication","description":"Write unit tests for new functionality","jobType":"REVIEW","jobState":"NEW","earnings":622.8,"companyId":"62","freelancerId":null},
{"title":"Optimize Database Queries","description":"Refactor code to improve readability","jobType":"OTHER","jobState":"NEW","earnings":394.9,"companyId":"95","freelancerId":null},
{"title":"Integrate Third-Party API","description":"Write unit tests for new functionality","jobType":"REVIEW","jobState":"NEW","earnings":718.0,"companyId":"74","freelancerId":null},
{"title":"Integrate Third-Party API","description":"Fix bug causing application crash","jobType":"TEST","jobState":"NEW","earnings":617.8,"companyId":"56","freelancerId":null},
{"title":"Refactor Frontend Components","description":"Refactor code to improve readability","jobType":"REVIEW","jobState":"NEW","earnings":199.2,"companyId":"63","freelancerId":null},
{"title":"Write Unit Tests","description":"Write unit tests for new functionality","jobType":"TEST","jobState":"NEW","earnings":554.7,"companyId":"54","freelancerId":null},
{"title":"Write Unit Tests","description":"Write unit tests for new functionality","jobType":"TEST","jobState":"NEW","earnings":424.8,"companyId":"65","freelancerId":null},
{"title":"Optimize Database Queries","description":"Fix bug causing application crash","jobType":"REVIEW","jobState":"NEW","earnings":901.0,"companyId":"94","freelancerId":null},
{"title":"Implement User Authentication","description":"Fix bug causing application crash","jobType":"TEST","jobState":"NEW","earnings":126.5,"companyId":"21","freelancerId":null},
{"title":"Implement User Authentication","description":"Implement user authentication feature","jobType":"OTHER","jobState":"NEW","earnings":537.4,"companyId":"77","freelancerId":null},
{"title":"Integrate Third-Party API","description":"Fix bug causing application crash","jobType":"TEST","jobState":"NEW","earnings":328.9,"companyId":"58","freelancerId":null},
{"title":"Write Unit Tests","description":"Write unit tests for new functionality","jobType":"TEST","jobState":"NEW","earnings":655.7,"companyId":"88","freelancerId":null},
{"title":"Refactor Frontend Components","description":"Refactor code to improve readability","jobType":"IMPLEMENT","jobState":"NEW","earnings":717.4,"companyId":"31","freelancerId":null},
{"title":"Integrate Third-Party API","description":"Implement user authentication feature","jobType":"IMPLEMENT","jobState":"NEW","earnings":724.6,"companyId":"86","freelancerId":null},
{"title":"Refactor Frontend Components","description":"Fix bug causing application crash","jobType":"IMPLEMENT","jobState":"NEW","earnings":300.0,"companyId":"29","freelancerId":null},
{"title":"Optimize Database Queries","description":"Optimize database queries for performance","jobType":"OTHER","jobState":"NEW","earnings":527.8,"companyId":"68","freelancerId":null},
{"title":"Optimize Database Queries","description":"Write unit tests for new functionality","jobType":"IMPLEMENT","jobState":"NEW","earnings":280.8,"companyId":"78","freelancerId":null},
{"title":"Implement User Authentication","description":"Fix bug causing application crash","jobType":"TEST","jobState":"NEW","earnings":865.1,"companyId":"97","freelancerId":null},
{"title":"Refactor Frontend Components","description":"Implement user authentication feature","jobType":"IMPLEMENT","jobState":"NEW","earnings":984.1,"companyId":"49","freelancerId":null},
{"title":"Write Unit Tests","description":"Implement user authentication feature","jobType":"TEST","jobState":"NEW","earnings":556.7,"companyId":"79","freelancerId":null},
{"title":"Optimize Database Queries","description":"Implement user authentication feature","jobType":"TEST","jobState":"NEW","earnings":672.2,"companyId":"96","freelancerId":null},
{"title":"Integrate Third-Party API","description":"Write unit tests for new functionality","jobType":"OTHER","jobState":"NEW","earnings":917.7,"companyId":"41","freelancerId":null},
{"title":"Implement User Authentication","description":"Fix bug causing application crash","jobType":"TEST","jobState":"NEW","earnings":878.4,"companyId":"42","freelancerId":null},
{"title":"Integrate Third-Party API","description":"Write unit tests for new functionality","jobType":"OTHER","jobState":"NEW","earnings":202.2,"companyId":"5","freelancerId":null},
{"title":"Refactor Frontend Components","description":"Fix bug causing application crash","jobType":"IMPLEMENT","jobState":"NEW","earnings":815.1,"companyId":"49","freelancerId":null},
{"title":"Implement User Authentication","description":"Write unit tests for new functionality","jobType":"TEST","jobState":"NEW","earnings":474.1,"companyId":"83","freelancerId":null},
{"title":"Refactor Frontend Components","description":"Fix bug causing application crash","jobType":"OTHER","jobState":"NEW","earnings":899.1,"companyId":"48","freelancerId":null},
{"title":"Write Unit Tests","description":"Implement user authentication feature","jobType":"TEST","jobState":"NEW","earnings":133.6,"companyId":"89","freelancerId":null},
{"title":"Optimize Database Queries","description":"Fix bug causing application crash","jobType":"REVIEW","jobState":"NEW","earnings":135.3,"companyId":"32","freelancerId":null},
{"title":"Refactor Frontend Components","description":"Implement user authentication feature","jobType":"IMPLEMENT","jobState":"NEW","earnings":914.0,"companyId":"77","freelancerId":null},
{"title":"Integrate Third-Party API","description":"Write unit tests for new functionality","jobType":"REVIEW","jobState":"NEW","earnings":388.3,"companyId":"7","freelancerId":null},
{"title":"Write Unit Tests","description":"Implement user authentication feature","jobType":"REVIEW","jobState":"NEW","earnings":666.6,"companyId":"94","freelancerId":null},
{"title":"Integrate Third-Party API","description":"Implement user authentication feature","jobType":"REVIEW","jobState":"NEW","earnings":558.9,"companyId":"83","freelancerId":null},
{"title":"Integrate Third-Party API","description":"Optimize database queries for performance","jobType":"TEST","jobState":"NEW","earnings":960.7,"companyId":"40","freelancerId":null},
{"title":"Write Unit Tests","description":"Write unit tests for new functionality","jobType":"TEST","jobState":"NEW","earnings":682.3,"companyId":"49","freelancerId":null},
{"title":"Optimize Database Queries","description":"Optimize database queries for performance","jobType":"REVIEW","jobState":"NEW","earnings":722.1,"companyId":"41","freelancerId":null},
{"title":"Refactor Frontend Components","description":"Implement user authentication feature","jobType":"IMPLEMENT","jobState":"NEW","earnings":675.4,"companyId":"44","freelancerId":null},
{"title":"Integrate Third-Party API","description":"Write unit tests for new functionality","jobType":"OTHER","jobState":"NEW","earnings":763.1,"companyId":"75","freelancerId":null},
{"title":"Integrate Third-Party API","description":"Write unit tests for new functionality","jobType":"REVIEW","jobState":"NEW","earnings":580.0,"companyId":"55","freelancerId":null},
{"title":"Implement User Authentication","description":"Fix bug causing application crash","jobType":"OTHER","jobState":"NEW","earnings":391.4,"companyId":"100","freelancerId":null},
{"title":"Optimize Database Queries","description":"Refactor code to improve readability","jobType":"TEST","jobState":"NEW","earnings":937.6,"companyId":"37","freelancerId":null},
{"title":"Optimize Database Queries","description":"Fix bug causing application crash","jobType":"OTHER","jobState":"NEW","earnings":283.3,"companyId":"82","freelancerId":null},
{"title":"Write Unit Tests","description":"Write unit tests for new functionality","jobType":"TEST","jobState":"NEW","earnings":541.7,"companyId":"72","freelancerId":null},
{"title":"Implement User Authentication","description":"Fix bug causing application crash","jobType":"OTHER","jobState":"NEW","earnings":626.1,"companyId":"31","freelancerId":null},
{"title":"Write Unit Tests","description":"Implement user authentication feature","jobType":"IMPLEMENT","jobState":"NEW","earnings":448.3,"companyId":"48","freelancerId":null},
{"title":"Write Unit Tests","description":"Optimize database queries for performance","jobType":"REVIEW","jobState":"NEW","earnings":144.4,"companyId":"96","freelancerId":null},
{"title":"Write Unit Tests","description":"Refactor code to improve readability","jobType":"OTHER","jobState":"NEW","earnings":109.5,"companyId":"9","freelancerId":null},
{"title":"Write Unit Tests","description":"Refactor code to improve readability","jobType":"IMPLEMENT","jobState":"NEW","earnings":796.2,"companyId":"38","freelancerId":null},
{"title":"Integrate Third-Party API","description":"Write unit tests for new functionality","jobType":"REVIEW","jobState":"NEW","earnings":563.7,"companyId":"20","freelancerId":null},
{"title":"Optimize Database Queries","description":"Write unit tests for new functionality","jobType":"IMPLEMENT","jobState":"NEW","earnings":634.0,"companyId":"57","freelancerId":null},
{"title":"Refactor Frontend Components","description":"Implement user authentication feature","jobType":"REVIEW","jobState":"NEW","earnings":953.7,"companyId":"28","freelancerId":null},
{"title":"Optimize Database Queries","description":"Fix bug causing application crash","jobType":"REVIEW","jobState":"NEW","earnings":996.3,"companyId":"30","freelancerId":null},
{"title":"Refactor Frontend Components","description":"Write unit tests for new functionality","jobType":"REVIEW","jobState":"NEW","earnings":587.8,"companyId":"77","freelancerId":null},
{"title":"Write Unit Tests","description":"Optimize database queries for performance","jobType":"TEST","jobState":"NEW","earnings":100.0,"companyId":"98","freelancerId":null},
{"title":"Integrate Third-Party API","description":"Write unit tests for new functionality","jobType":"REVIEW","jobState":"NEW","earnings":840.8,"companyId":"47","freelancerId":null},
{"title":"Refactor Frontend Components","description":"Implement user authentication feature","jobType":"OTHER","jobState":"NEW","earnings":473.2,"companyId":"37","freelancerId":null},
{"title":"Refactor Frontend Components","description":"Fix bug causing application crash","jobType":"TEST","jobState":"NEW","earnings":916.7,"companyId":"69","freelancerId":null},
{"title":"Optimize Database Queries","description":"Fix bug causing application crash","jobType":"TEST","jobState":"NEW","earnings":767.4,"companyId":"100","freelancerId":null},
{"title":"Implement User Authentication","description":"Refactor code to improve readability","jobType":"TEST","jobState":"NEW","earnings":419.7,"companyId":"96","freelancerId":null},
{"title":"Refactor Frontend Components","description":"Write unit tests for new functionality","jobType":"TEST","jobState":"NEW","earnings":815.6,"companyId":"71","freelancerId":null},
{"title":"Write Unit Tests","description":"Optimize database queries for performance","jobType":"OTHER","jobState":"NEW","earnings":285.5,"companyId":"75","freelancerId":null},
{"title":"Integrate Third-Party API","description":"Implement user authentication feature","jobType":"OTHER","jobState":"NEW","earnings":987.9,"companyId":"8","freelancerId":null},
{"title":"Write Unit Tests","description":"Implement user authentication feature","jobType":"REVIEW","jobState":"NEW","earnings":172.5,"companyId":"71","freelancerId":null},
{"title":"Integrate Third-Party API","description":"Refactor code to improve readability","jobType":"IMPLEMENT","jobState":"NEW","earnings":416.3,"companyId":"46","freelancerId":null},
{"title":"Implement User Authentication","description":"Optimize database queries for performance","jobType":"TEST","jobState":"NEW","earnings":855.2,"companyId":"90","freelancerId":null},
{"title":"Integrate Third-Party API","description":"Optimize database queries for performance","jobType":"IMPLEMENT","jobState":"NEW","earnings":589.1,"companyId":"11","freelancerId":null},
{"title":"Integrate Third-Party API","description":"Refactor code to improve readability","jobType":"OTHER","jobState":"NEW","earnings":334.6,"companyId":"47","freelancerId":null},
{"title":"Optimize Database Queries","description":"Implement user authentication feature","jobType":"REVIEW","jobState":"NEW","earnings":930.7,"companyId":"90","freelancerId":null},
{"title":"Integrate Third-Party API","description":"Implement user authentication feature","jobType":"OTHER","jobState":"NEW","earnings":694.6,"companyId":"88","freelancerId":null},
{"title":"Implement User Authentication","description":"Implement user authentication feature","jobType":"TEST","jobState":"NEW","earnings":290.6,"companyId":"85","freelancerId":null},
{"title":"Refactor Frontend Components","description":"Fix bug causing application crash","jobType":"TEST","jobState":"NEW","earnings":465.0,"companyId":"45","freelancerId":null},
{"title":"Implement User Authentication","description":"Implement user authentication feature","jobType":"TEST","jobState":"NEW","earnings":236.6,"companyId":"60","freelancerId":null},
{"title":"Implement User Authentication","description":"Implement user authentication feature","jobType":"REVIEW","jobState":"NEW","earnings":949.2,"companyId":"85","freelancerId":null},
{"title":"Implement User Authentication","description":"Optimize database queries for performance","jobType":"TEST","jobState":"NEW","earnings":610.5,"companyId":"12","freelancerId":null},
{"title":"Write Unit Tests","description":"Fix bug causing application crash","jobType":"REVIEW","jobState":"NEW","earnings":961.2,"companyId":"57","freelancerId":null},
{"title":"Refactor Frontend Components","description":"Optimize database queries for performance","jobType":"IMPLEMENT","jobState":"NEW","earnings":610.9,"companyId":"52","freelancerId":null},
{"title":"Integrate Third-Party API","description":"Optimize database queries for performance","jobType":"OTHER","jobState":"NEW","earnings":172.7,"companyId":"71","freelancerId":null},
{"title":"Write Unit Tests","description":"Optimize database queries for performance","jobType":"TEST","jobState":"NEW","earnings":697.7,"companyId":"26","freelancerId":null},
{"title":"Write Unit Tests","description":"Write unit tests for new functionality","jobType":"IMPLEMENT","jobState":"NEW","earnings":160.7,"companyId":"89","freelancerId":null},
{"title":"Optimize Database Queries","description":"Refactor code to improve readability","jobType":"OTHER","jobState":"NEW","earnings":109.4,"companyId":"23","freelancerId":null},
{"title":"Write Unit Tests","description":"Fix bug causing application crash","jobType":"TEST","jobState":"NEW","earnings":525.7,"companyId":"57","freelancerId":null},
{"title":"Integrate Third-Party API","description":"Optimize database queries for performance","jobType":"OTHER","jobState":"NEW","earnings":682.6,"companyId":"43","freelancerId":null},
{"title":"Refactor Frontend Components","description":"Implement user authentication feature","jobType":"REVIEW","jobState":"NEW","earnings":872.9,"companyId":"36","freelancerId":null},
{"title":"Write Unit Tests","description":"Write unit tests for new functionality","jobType":"IMPLEMENT","jobState":"NEW","earnings":596.8,"companyId":"93","freelancerId":null},
{"title":"Write Unit Tests","description":"Implement user authentication feature","jobType":"REVIEW","jobState":"NEW","earnings":462.1,"companyId":"23","freelancerId":null},
{"title":"Write Unit Tests","description":"Implement user authentication feature","jobType":"REVIEW","jobState":"NEW","earnings":195.7,"companyId":"53","freelancerId":null},
{"title":"Implement User Authentication","description":"Write unit tests for new functionality","jobType":"TEST","jobState":"NEW","earnings":645.6,"companyId":"73","freelancerId":null},
{"title":"Refactor Frontend Components","description":"Implement user authentication feature","jobType":"OTHER","jobState":"NEW","earnings":320.1,"companyId":"22","freelancerId":null},
{"title":"Integrate Third-Party API","description":"Optimize database queries for performance","jobType":"OTHER","jobState":"NEW","earnings":747.3,"companyId":"94","freelancerId":null},
{"title":"Integrate Third-Party API","description":"Fix bug causing application crash","jobType":"IMPLEMENT","jobState":"NEW","earnings":475.0,"companyId":"30","freelancerId":null},
{"title":"Optimize Database Queries","description":"Optimize database queries for performance","jobType":"IMPLEMENT","jobState":"NEW","earnings":500.1,"companyId":"78","freelancerId":null},
{"title":"Implement User Authentication","description":"Fix bug causing application crash","jobType":"REVIEW","jobState":"NEW","earnings":946.0,"companyId":"70","freelancerId":null},
{"title":"Integrate Third-Party API","description":"Implement user authentication feature","jobType":"OTHER","jobState":"NEW","earnings":400.4,"companyId":"74","freelancerId":null},
{"title":"Optimize Database Queries","description":"Refactor code to improve readability","jobType":"REVIEW","jobState":"NEW","earnings":796.3,"companyId":"100","freelancerId":null},
{"title":"Write Unit Tests","description":"Optimize database queries for performance","jobType":"TEST","jobState":"NEW","earnings":979.1,"companyId":"41","freelancerId":null},
{"title":"Integrate Third-Party API","description":"Fix bug causing application crash","jobType":"IMPLEMENT","jobState":"NEW","earnings":472.6,"companyId":"67","freelancerId":null},
{"title":"Integrate Third-Party API","description":"Refactor code to improve readability","jobType":"OTHER","jobState":"NEW","earnings":411.8,"companyId":"77","freelancerId":null},
{"title":"Integrate Third-Party API","description":"Optimize database queries for performance","jobType":"TEST","jobState":"NEW","earnings":166.8,"companyId":"22","freelancerId":null},
{"title":"Refactor Frontend Components","description":"Fix bug causing application crash","jobType":"OTHER","jobState":"NEW","earnings":394.1,"companyId":"49","freelancerId":null},
{"title":"Implement User Authentication","description":"Fix bug causing application crash","jobType":"TEST","jobState":"NEW","earnings":765.5,"companyId":"45","freelancerId":null},
{"title":"Integrate Third-Party API","description":"Fix bug causing application crash","jobType":"TEST","jobState":"NEW","earnings":157.0,"companyId":"81","freelancerId":null},
{"title":"Refactor Frontend Components","description":"Fix bug causing application crash","jobType":"IMPLEMENT","jobState":"NEW","earnings":949.2,"companyId":"74","freelancerId":null},
{"title":"Write Unit Tests","description":"Implement user authentication feature","jobType":"OTHER","jobState":"NEW","earnings":898.0,"companyId":"70","freelancerId":null},
{"title":"Write Unit Tests","description":"Refactor code to improve readability","jobType":"REVIEW","jobState":"NEW","earnings":939.0,"companyId":"15","freelancerId":null},
{"title":"Integrate Third-Party API","description":"Fix bug causing application crash","jobType":"OTHER","jobState":"NEW","earnings":250.6,"companyId":"48","freelancerId":null},
{"title":"Optimize Database Queries","description":"Implement user authentication feature","jobType":"REVIEW","jobState":"NEW","earnings":980.2,"companyId":"42","freelancerId":null},
{"title":"Refactor Frontend Components","description":"Write unit tests for new functionality","jobType":"OTHER","jobState":"NEW","earnings":907.4,"companyId":"42","freelancerId":null},
{"title":"Integrate Third-Party API","description":"Optimize database queries for performance","jobType":"IMPLEMENT","jobState":"NEW","earnings":459.4,"companyId":"96","freelancerId":null},
{"title":"Integrate Third-Party API","description":"Optimize database queries for performance","jobType":"IMPLEMENT","jobState":"NEW","earnings":866.3,"companyId":"27","freelancerId":null},
{"title":"Refactor Frontend Components","description":"Write unit tests for new functionality","jobType":"OTHER","jobState":"NEW","earnings":451.3,"companyId":"33","freelancerId":null},
{"title":"Implement User Authentication","description":"Implement user authentication feature","jobType":"OTHER","jobState":"NEW","earnings":614.7,"companyId":"79","freelancerId":null},
{"title":"Write Unit Tests","description":"Refactor code to improve readability","jobType":"REVIEW","jobState":"NEW","earnings":668.1,"companyId":"59","freelancerId":null},
{"title":"Integrate Third-Party API","description":"Optimize database queries for performance","jobType":"TEST","jobState":"NEW","earnings":929.7,"companyId":"94","freelancerId":null},
{"title":"Write Unit Tests","description":"Optimize database queries for performance","jobType":"REVIEW","jobState":"NEW","earnings":105.1,"companyId":"81","freelancerId":null},
{"title":"Refactor Frontend Components","description":"Implement user authentication feature","jobType":"TEST","jobState":"NEW","earnings":488.2,"companyId":"94","freelancerId":null},
{"title":"Implement User Authentication","description":"Optimize database queries for performance","jobType":"IMPLEMENT","jobState":"NEW","earnings":161.0,"companyId":"15","freelancerId":null},
{"title":"Refactor Frontend Components","description":"Fix bug causing application crash","jobType":"OTHER","jobState":"NEW","earnings":985.8,"companyId":"27","freelancerId":null},
{"title":"Implement User Authentication","description":"Refactor code to improve readability","jobType":"REVIEW","jobState":"NEW","earnings":764.8,"companyId":"77","freelancerId":null},
{"title":"Implement User Authentication","description":"Refactor code to improve readability","jobType":"OTHER","jobState":"NEW","earnings":387.0,"companyId":"17","freelancerId":null},
{"title":"Optimize Database Queries","description":"Refactor code to improve readability","jobType":"IMPLEMENT","jobState":"NEW","earnings":112.7,"companyId":"71","freelancerId":null},
{"title":"Refactor Frontend Components","description":"Refactor code to improve readability","jobType":"OTHER","jobState":"NEW","earnings":423.7,"companyId":"2","freelancerId":null},
{"title":"Integrate Third-Party API","description":"Refactor code to improve readability","jobType":"REVIEW","jobState":"NEW","earnings":907.7,"companyId":"32","freelancerId":null},
{"title":"Refactor Frontend Components","description":"Write unit tests for new functionality","jobType":"IMPLEMENT","jobState":"NEW","earnings":200.9,"companyId":"25","freelancerId":null},
{"title":"Optimize Database Queries","description":"Optimize database queries for performance","jobType":"TEST","jobState":"NEW","earnings":891.7,"companyId":"83","freelancerId":null},
{"title":"Write Unit Tests","description":"Implement user authentication feature","jobType":"IMPLEMENT","jobState":"NEW","earnings":231.3,"companyId":"94","freelancerId":null},
{"title":"Integrate Third-Party API","description":"Optimize database queries for performance","jobType":"OTHER","jobState":"NEW","earnings":584.6,"companyId":"47","freelancerId":null},
{"title":"Optimize Database Queries","description":"Implement user authentication feature","jobType":"REVIEW","jobState":"NEW","earnings":921.9,"companyId":"45","freelancerId":null},
{"title":"Integrate Third-Party API","description":"Refactor code to improve readability","jobType":"TEST","jobState":"NEW","earnings":793.7,"companyId":"88","freelancerId":null},
{"title":"Optimize Database Queries","description":"Optimize database queries for performance","jobType":"TEST","jobState":"NEW","earnings":161.4,"companyId":"94","freelancerId":null},
{"title":"Implement User Authentication","description":"Implement user authentication feature","jobType":"REVIEW","jobState":"NEW","earnings":949.9,"companyId":"80","freelancerId":null},
{"title":"Refactor Frontend Components","description":"Fix bug causing application crash","jobType":"IMPLEMENT","jobState":"NEW","earnings":717.6,"companyId":"89","freelancerId":null},
{"title":"Integrate Third-Party API","description":"Fix bug causing application crash","jobType":"IMPLEMENT","jobState":"NEW","earnings":622.6,"companyId":"62","freelancerId":null},
{"title":"Optimize Database Queries","description":"Refactor code to improve readability","jobType":"IMPLEMENT","jobState":"NEW","earnings":417.0,"companyId":"31","freelancerId":null},
{"title":"Implement User Authentication","description":"Implement user authentication feature","jobType":"REVIEW","jobState":"NEW","earnings":722.0,"companyId":"49","freelancerId":null},
{"title":"Refactor Frontend Components","description":"Fix bug causing application crash","jobType":"TEST","jobState":"NEW","earnings":300.0,"companyId":"87","freelancerId":null},
{"title":"Optimize Database Queries","description":"Fix bug causing application crash","jobType":"TEST","jobState":"NEW","earnings":376.3,"companyId":"11","freelancerId":null},
{"title":"Write Unit Tests","description":"Implement user authentication feature","jobType":"IMPLEMENT","jobState":"NEW","earnings":377.7,"companyId":"51","freelancerId":null},
{"title":"Integrate Third-Party API","description":"Write unit tests for new functionality","jobType":"IMPLEMENT","jobState":"NEW","earnings":726.1,"companyId":"90","freelancerId":null},
{"title":"Write Unit Tests","description":"Fix bug causing application crash","jobType":"TEST","jobState":"NEW","earnings":207.3,"companyId":"57","freelancerId":null},
{"title":"Refactor Frontend Components","description":"Implement user authentication feature","jobType":"TEST","jobState":"NEW","earnings":208.3,"companyId":"78","freelancerId":null},
{"title":"Write Unit Tests","description":"Write unit tests for new functionality","jobType":"IMPLEMENT","jobState":"NEW","earnings":682.9,"companyId":"3","freelancerId":null},
{"title":"Integrate Third-Party API","description":"Write unit tests for new functionality","jobType":"OTHER","jobState":"NEW","earnings":819.2,"companyId":"12","freelancerId":null},
{"title":"Implement User Authentication","description":"Refactor code to improve readability","jobType":"OTHER","jobState":"NEW","earnings":670.8,"companyId":"35","freelancerId":null},
{"title":"Refactor Frontend Components","description":"Implement user authentication feature","jobType":"REVIEW","jobState":"NEW","earnings":718.5,"companyId":"69","freelancerId":null},
{"title":"Optimize Database Queries","description":"Optimize database queries for performance","jobType":"REVIEW","jobState":"NEW","earnings":684.1,"companyId":"55","freelancerId":null},
{"title":"Implement User Authentication","description":"Implement user authentication feature","jobType":"IMPLEMENT","jobState":"NEW","earnings":379.9,"companyId":"51","freelancerId":null},
{"title":"Optimize Database Queries","description":"Refactor code to improve readability","jobType":"REVIEW","jobState":"NEW","earnings":858.2,"companyId":"3","freelancerId":null},
{"title":"Integrate Third-Party API","description":"Optimize database queries for performance","jobType":"REVIEW","jobState":"NEW","earnings":112.1,"companyId":"72","freelancerId":null},
{"title":"Implement User Authentication","description":"Optimize database queries for performance","jobType":"IMPLEMENT","jobState":"NEW","earnings":114.6,"companyId":"3","freelancerId":null},
{"title":"Write Unit Tests","description":"Implement user authentication feature","jobType":"TEST","jobState":"NEW","earnings":758.1,"companyId":"50","freelancerId":null},
{"title":"Refactor Frontend Components","description":"Implement user authentication feature","jobType":"OTHER","jobState":"NEW","earnings":249.3,"companyId":"87","freelancerId":null},
{"title":"Write Unit Tests","description":"Optimize database queries for performance","jobType":"REVIEW","jobState":"NEW","earnings":130.8,"companyId":"68","freelancerId":null},
{"title":"Write Unit Tests","description":"Fix bug causing application crash","jobType":"OTHER","jobState":"NEW","earnings":641.6,"companyId":"91","freelancerId":null},
{"title":"Optimize Database Queries","description":"Write unit tests for new functionality","jobType":"TEST","jobState":"NEW","earnings":293.4,"companyId":"95","freelancerId":null},
{"title":"Refactor Frontend Components","description":"Write unit tests for new functionality","jobType":"REVIEW","jobState":"NEW","earnings":455.6,"companyId":"63","freelancerId":null},
{"title":"Write Unit Tests","description":"Implement user authentication feature","jobType":"TEST","jobState":"NEW","earnings":503.9,"companyId":"64","freelancerId":null},
{"title":"Write Unit Tests","description":"Implement user authentication feature","jobType":"REVIEW","jobState":"NEW","earnings":862.4,"companyId":"93","freelancerId":null},
{"title":"Implement User Authentication","description":"Refactor code to improve readability","jobType":"OTHER","jobState":"NEW","earnings":937.3,"companyId":"46","freelancerId":null},
{"title":"Refactor Frontend Components","description":"Write unit tests for new functionality","jobType":"REVIEW","jobState":"NEW","earnings":523.0,"companyId":"10","freelancerId":null},
{"title":"Optimize Database Queries","description":"Fix bug causing application crash","jobType":"TEST","jobState":"NEW","earnings":694.8,"companyId":"33","freelancerId":null},
{"title":"Refactor Frontend Components","description":"Write unit tests for new functionality","jobType":"TEST","jobState":"NEW","earnings":565.9,"companyId":"33","freelancerId":null},
{"title":"Integrate Third-Party API","description":"Write unit tests for new functionality","jobType":"OTHER","jobState":"NEW","earnings":350.1,"companyId":"59","freelancerId":null},
{"title":"Refactor Frontend Components","description":"Implement user authentication feature","jobType":"TEST","jobState":"NEW","earnings":351.1,"companyId":"20","freelancerId":null},
{"title":"Implement User Authentication","description":"Optimize database queries for performance","jobType":"TEST","jobState":"NEW","earnings":774.7,"companyId":"92","freelancerId":null},
{"title":"Optimize Database Queries","description":"Refactor code to improve readability","jobType":"REVIEW","jobState":"NEW","earnings":727.8,"companyId":"57","freelancerId":null},
{"title":"Implement User Authentication","description":"Implement user authentication feature","jobType":"OTHER","jobState":"NEW","earnings":281.7,"companyId":"93","freelancerId":null},
{"title":"Optimize Database Queries","description":"Fix bug causing application crash","jobType":"REVIEW","jobState":"NEW","earnings":346.7,"companyId":"59","freelancerId":null},
{"title":"Optimize Database Queries","description":"Refactor code to improve readability","jobType":"REVIEW","jobState":"NEW","earnings":540.4,"companyId":"67","freelancerId":null},
{"title":"Implement User Authentication","description":"Implement user authentication feature","jobType":"IMPLEMENT","jobState":"NEW","earnings":146.6,"companyId":"24","freelancerId":null},
{"title":"Implement User Authentication","description":"Optimize database queries for performance","jobType":"OTHER","jobState":"NEW","earnings":704.1,"companyId":"79","freelancerId":null},
{"title":"Integrate Third-Party API","description":"Optimize database queries for performance","jobType":"IMPLEMENT","jobState":"NEW","earnings":144.6,"companyId":"97","freelancerId":null},
{"title":"Implement User Authentication","description":"Write unit tests for new functionality","jobType":"OTHER","jobState":"NEW","earnings":786.1,"companyId":"55","freelancerId":null},
{"title":"Integrate Third-Party API","description":"Write unit tests for new functionality","jobType":"OTHER","jobState":"NEW","earnings":873.2,"companyId":"68","freelancerId":null},
{"title":"Integrate Third-Party API","description":"Optimize database queries for performance","jobType":"IMPLEMENT","jobState":"NEW","earnings":162.0,"companyId":"40","freelancerId":null},
{"title":"Optimize Database Queries","description":"Write unit tests for new functionality","jobType":"OTHER","jobState":"NEW","earnings":702.6,"companyId":"89","freelancerId":null},
{"title":"Implement User Authentication","description":"Write unit tests for new functionality","jobType":"REVIEW","jobState":"NEW","earnings":512.2,"companyId":"67","freelancerId":null},
{"title":"Integrate Third-Party API","description":"Optimize database queries for performance","jobType":"OTHER","jobState":"NEW","earnings":808.0,"companyId":"34","freelancerId":null},
{"title":"Integrate Third-Party API","description":"Write unit tests for new functionality","jobType":"IMPLEMENT","jobState":"NEW","earnings":707.0,"companyId":"59","freelancerId":null},
{"title":"Implement User Authentication","description":"Write unit tests for new functionality","jobType":"TEST","jobState":"NEW","earnings":291.2,"companyId":"22","freelancerId":null},
{"title":"Implement User Authentication","description":"Write unit tests for new functionality","jobType":"TEST","jobState":"NEW","earnings":564.2,"companyId":"2","freelancerId":null},
{"title":"Write Unit Tests","description":"Refactor code to improve readability","jobType":"IMPLEMENT","jobState":"NEW","earnings":976.1,"companyId":"10","freelancerId":null},
{"title":"Integrate Third-Party API","description":"Write unit tests for new functionality","jobType":"TEST","jobState":"NEW","earnings":419.1,"companyId":"47","freelancerId":null},
{"title":"Write Unit Tests","description":"Implement user authentication feature","jobType":"TEST","jobState":"NEW","earnings":367.6,"companyId":"72","freelancerId":null},
{"title":"Refactor Frontend Components","description":"Optimize database queries for performance","jobType":"OTHER","jobState":"NEW","earnings":131.9,"companyId":"67","freelancerId":null},
{"title":"Optimize Database Queries","description":"Fix bug causing application crash","jobType":"TEST","jobState":"NEW","earnings":124.2,"companyId":"65","freelancerId":null},
{"title":"Optimize Database Queries","description":"Refactor code to improve readability","jobType":"REVIEW","jobState":"NEW","earnings":150.5,"companyId":"54","freelancerId":null},
{"title":"Refactor Frontend Components","description":"Write unit tests for new functionality","jobType":"TEST","jobState":"NEW","earnings":255.7,"companyId":"25","freelancerId":null},
{"title":"Implement User Authentication","description":"Implement user authentication feature","jobType":"IMPLEMENT","jobState":"NEW","earnings":633.2,"companyId":"85","freelancerId":null},
{"title":"Integrate Third-Party API","description":"Write unit tests for new functionality","jobType":"IMPLEMENT","jobState":"NEW","earnings":125.5,"companyId":"46","freelancerId":null},
{"title":"Integrate Third-Party API","description":"Fix bug causing application crash","jobType":"REVIEW","jobState":"NEW","earnings":259.8,"companyId":"59","freelancerId":null},
{"title":"Write Unit Tests","description":"Write unit tests for new functionality","jobType":"IMPLEMENT","jobState":"NEW","earnings":292.4,"companyId":"67","freelancerId":null},
{"title":"Refactor Frontend Components","description":"Refactor code to improve readability","jobType":"IMPLEMENT","jobState":"NEW","earnings":278.8,"companyId":"78","freelancerId":null},
{"title":"Optimize Database Queries","description":"Write unit tests for new functionality","jobType":"TEST","jobState":"NEW","earnings":522.5,"companyId":"82","freelancerId":null},
{"title":"Optimize Database Queries","description":"Write unit tests for new functionality","jobType":"REVIEW","jobState":"NEW","earnings":177.8,"companyId":"65","freelancerId":null},
{"title":"Write Unit Tests","description":"Implement user authentication feature","jobType":"TEST","jobState":"NEW","earnings":885.7,"companyId":"42","freelancerId":null},
{"title":"Optimize Database Queries","description":"Implement user authentication feature","jobType":"IMPLEMENT","jobState":"NEW","earnings":360.8,"companyId":"48","freelancerId":null},
{"title":"Write Unit Tests","description":"Write unit tests for new functionality","jobType":"TEST","jobState":"NEW","earnings":709.7,"companyId":"57","freelancerId":null},
{"title":"Implement User Authentication","description":"Fix bug causing application crash","jobType":"TEST","jobState":"NEW","earnings":729.3,"companyId":"95","freelancerId":null},
{"title":"Implement User Authentication","description":"Implement user authentication feature","jobType":"TEST","jobState":"NEW","earnings":487.5,"companyId":"35","freelancerId":null},
{"title":"Write Unit Tests","description":"Optimize database queries for performance","jobType":"TEST","jobState":"NEW","earnings":748.7,"companyId":"16","freelancerId":null},
{"title":"Optimize Database Queries","description":"Fix bug causing application crash","jobType":"TEST","jobState":"NEW","earnings":334.0,"companyId":"4","freelancerId":null},
{"title":"Implement User Authentication","description":"Implement user authentication feature","jobType":"OTHER","jobState":"NEW","earnings":258.3,"companyId":"86","freelancerId":null},
{"title":"Refactor Frontend Components","description":"Implement user authentication feature","jobType":"TEST","jobState":"NEW","earnings":711.6,"companyId":"80","freelancerId":null},
{"title":"Optimize Database Queries","description":"Fix bug causing application crash","jobType":"TEST","jobState":"NEW","earnings":771.4,"companyId":"100","freelancerId":null},
{"title":"Implement User Authentication","description":"Implement user authentication feature","jobType":"TEST","jobState":"NEW","earnings":375.6,"companyId":"22","freelancerId":null},
{"title":"Refactor Frontend Components","description":"Optimize database queries for performance","jobType":"TEST","jobState":"NEW","earnings":656.5,"companyId":"97","freelancerId":null},
{"title":"Integrate Third-Party API","description":"Write unit tests for new functionality","jobType":"TEST","jobState":"NEW","earnings":126.5,"companyId":"79","freelancerId":null},
{"title":"Write Unit Tests","description":"Write unit tests for new functionality","jobType":"TEST","jobState":"NEW","earnings":736.5,"companyId":"94","freelancerId":null},
{"title":"Write Unit Tests","description":"Implement user authentication feature","jobType":"REVIEW","jobState":"NEW","earnings":530.3,"companyId":"75","freelancerId":null},
{"title":"Optimize Database Queries","description":"Refactor code to improve readability","jobType":"IMPLEMENT","jobState":"NEW","earnings":240.1,"companyId":"16","freelancerId":null},
{"title":"Write Unit Tests","description":"Refactor code to improve readability","jobType":"OTHER","jobState":"NEW","earnings":914.2,"companyId":"27","freelancerId":null},
{"title":"Refactor Frontend Components","description":"Implement user authentication feature","jobType":"REVIEW","jobState":"NEW","earnings":782.0,"companyId":"54","freelancerId":null},
{"title":"Integrate Third-Party API","description":"Write unit tests for new functionality","jobType":"OTHER","jobState":"NEW","earnings":360.6,"companyId":"2","freelancerId":null},
{"title":"Refactor Frontend Components","description":"Write unit tests for new functionality","jobType":"REVIEW","jobState":"NEW","earnings":291.0,"companyId":"56","freelancerId":null},
{"title":"Integrate Third-Party API","description":"Refactor code to improve readability","jobType":"TEST","jobState":"NEW","earnings":129.9,"companyId":"90","freelancerId":null},
{"title":"Refactor Frontend Components","description":"Optimize database queries for performance","jobType":"REVIEW","jobState":"NEW","earnings":226.9,"companyId":"20","freelancerId":null},
{"title":"Integrate Third-Party API","description":"Refactor code to improve readability","jobType":"REVIEW","jobState":"NEW","earnings":653.1,"companyId":"93","freelancerId":null},
{"title":"Optimize Database Queries","description":"Refactor code to improve readability","jobType":"IMPLEMENT","jobState":"NEW","earnings":231.8,"companyId":"25","freelancerId":null},
{"title":"Implement User Authentication","description":"Fix bug causing application crash","jobType":"OTHER","jobState":"NEW","earnings":872.6,"companyId":"12","freelancerId":null},
{"title":"Implement User Authentication","description":"Optimize database queries for performance","jobType":"TEST","jobState":"NEW","earnings":204.0,"companyId":"71","freelancerId":null},
{"title":"Refactor Frontend Components","description":"Optimize database queries for performance","jobType":"REVIEW","jobState":"NEW","earnings":282.1,"companyId":"6","freelancerId":null},
{"title":"Refactor Frontend Components","description":"Implement user authentication feature","jobType":"OTHER","jobState":"NEW","earnings":577.9,"companyId":"79","freelancerId":null},
{"title":"Refactor Frontend Components","description":"Refactor code to improve readability","jobType":"OTHER","jobState":"NEW","earnings":129.0,"companyId":"25","freelancerId":null},
{"title":"Write Unit Tests","description":"Optimize database queries for performance","jobType":"TEST","jobState":"NEW","earnings":714.6,"companyId":"6","freelancerId":null},
{"title":"Implement User Authentication","description":"Implement user authentication feature","jobType":"IMPLEMENT","jobState":"NEW","earnings":536.4,"companyId":"71","freelancerId":null},
{"title":"Write Unit Tests","description":"Implement user authentication feature","jobType":"REVIEW","jobState":"NEW","earnings":878.5,"companyId":"31","freelancerId":null},
{"title":"Refactor Frontend Components","description":"Write unit tests for new functionality","jobType":"TEST","jobState":"NEW","earnings":519.0,"companyId":"32","freelancerId":null},
{"title":"Refactor Frontend Components","description":"Refactor code to improve readability","jobType":"REVIEW","jobState":"NEW","earnings":557.0,"companyId":"18","freelancerId":null},
{"title":"Optimize Database Queries","description":"Implement user authentication feature","jobType":"OTHER","jobState":"NEW","earnings":366.7,"companyId":"78","freelancerId":null},
{"title":"Write Unit Tests","description":"Implement user authentication feature","jobType":"REVIEW","jobState":"NEW","earnings":469.8,"companyId":"73","freelancerId":null},
{"title":"Implement User Authentication","description":"Optimize database queries for performance","jobType":"OTHER","jobState":"NEW","earnings":658.1,"companyId":"27","freelancerId":null},
{"title":"Optimize Database Queries","description":"Refactor code to improve readability","jobType":"REVIEW","jobState":"NEW","earnings":556.9,"companyId":"58","freelancerId":null},
{"title":"Implement User Authentication","description":"Fix bug causing application crash","jobType":"TEST","jobState":"NEW","earnings":765.9,"companyId":"36","freelancerId":null},
{"title":"Implement User Authentication","description":"Implement user authentication feature","jobType":"REVIEW","jobState":"NEW","earnings":899.1,"companyId":"51","freelancerId":null},
{"title":"Integrate Third-Party API","description":"Write unit tests for new functionality","jobType":"IMPLEMENT","jobState":"NEW","earnings":500.1,"companyId":"79","freelancerId":null},
{"title":"Optimize Database Queries","description":"Optimize database queries for performance","jobType":"IMPLEMENT","jobState":"NEW","earnings":308.4,"companyId":"36","freelancerId":null},
{"title":"Refactor Frontend Components","description":"Write unit tests for new functionality","jobType":"IMPLEMENT","jobState":"NEW","earnings":797.1,"companyId":"63","freelancerId":null},
{"title":"Write Unit Tests","description":"Implement user authentication feature","jobType":"TEST","jobState":"NEW","earnings":246.7,"companyId":"41","freelancerId":null},
{"title":"Implement User Authentication","description":"Implement user authentication feature","jobType":"REVIEW","jobState":"NEW","earnings":708.6,"companyId":"92","freelancerId":null},
{"title":"Implement User Authentication","description":"Fix bug causing application crash","jobType":"OTHER","jobState":"NEW","earnings":438.1,"companyId":"41","freelancerId":null},
{"title":"Write Unit Tests","description":"Refactor code to improve readability","jobType":"TEST","jobState":"NEW","earnings":983.5,"companyId":"51","freelancerId":null},
{"title":"Optimize Database Queries","description":"Optimize database queries for performance","jobType":"IMPLEMENT","jobState":"NEW","earnings":968.5,"companyId":"65","freelancerId":null},
{"title":"Write Unit Tests","description":"Fix bug causing application crash","jobType":"TEST","jobState":"NEW","earnings":264.3,"companyId":"70","freelancerId":null},
{"title":"Implement User Authentication","description":"Optimize database queries for performance","jobType":"IMPLEMENT","jobState":"NEW","earnings":244.7,"companyId":"56","freelancerId":null},
{"title":"Write Unit Tests","description":"Refactor code to improve readability","jobType":"TEST","jobState":"NEW","earnings":304.4,"companyId":"69","freelancerId":null},
{"title":"Write Unit Tests","description":"Optimize database queries for performance","jobType":"OTHER","jobState":"NEW","earnings":405.9,"companyId":"94","freelancerId":null},
{"title":"Write Unit Tests","description":"Write unit tests for new functionality","jobType":"IMPLEMENT","jobState":"NEW","earnings":777.7,"companyId":"42","freelancerId":null},
{"title":"Refactor Frontend Components","description":"Write unit tests for new functionality","jobType":"REVIEW","jobState":"NEW","earnings":864.2,"companyId":"48","freelancerId":null},
{"title":"Refactor Frontend Components","description":"Optimize database queries for performance","jobType":"OTHER","jobState":"NEW","earnings":851.9,"companyId":"13","freelancerId":null},
{"title":"Write Unit Tests","description":"Optimize database queries for performance","jobType":"OTHER","jobState":"NEW","earnings":177.5,"companyId":"28","freelancerId":null},
{"title":"Refactor Frontend Components","description":"Fix bug causing application crash","jobType":"TEST","jobState":"NEW","earnings":803.9,"companyId":"26","freelancerId":null},
{"title":"Implement User Authentication","description":"Optimize database queries for performance","jobType":"REVIEW","jobState":"NEW","earnings":568.6,"companyId":"61","freelancerId":null},
{"title":"Implement User Authentication","description":"Fix bug causing application crash","jobType":"REVIEW","jobState":"NEW","earnings":524.3,"companyId":"85","freelancerId":null},
{"title":"Write Unit Tests","description":"Fix bug causing application crash","jobType":"IMPLEMENT","jobState":"NEW","earnings":187.0,"companyId":"56","freelancerId":null},
{"title":"Integrate Third-Party API","description":"Optimize database queries for performance","jobType":"TEST","jobState":"NEW","earnings":443.4,"companyId":"33","freelancerId":null},
{"title":"Optimize Database Queries","description":"Refactor code to improve readability","jobType":"IMPLEMENT","jobState":"NEW","earnings":802.5,"companyId":"41","freelancerId":null},
{"title":"Optimize Database Queries","description":"Fix bug causing application crash","jobType":"REVIEW","jobState":"NEW","earnings":487.4,"companyId":"83","freelancerId":null},
{"title":"Optimize Database Queries","description":"Refactor code to improve readability","jobType":"IMPLEMENT","jobState":"NEW","earnings":667.5,"companyId":"94","freelancerId":null},
{"title":"Write Unit Tests","description":"Implement user authentication feature","jobType":"REVIEW","jobState":"NEW","earnings":353.2,"companyId":"99","freelancerId":null},
{"title":"Refactor Frontend Components","description":"Refactor code to improve readability","jobType":"IMPLEMENT","jobState":"NEW","earnings":936.6,"companyId":"38","freelancerId":null},
{"title":"Integrate Third-Party API","description":"Refactor code to improve readability","jobType":"OTHER","jobState":"NEW","earnings":759.3,"companyId":"5","freelancerId":null},
{"title":"Optimize Database Queries","description":"Optimize database queries for performance","jobType":"TEST","jobState":"NEW","earnings":352.5,"companyId":"66","freelancerId":null},
{"title":"Integrate Third-Party API","description":"Write unit tests for new functionality","jobType":"OTHER","jobState":"NEW","earnings":622.6,"companyId":"76","freelancerId":null},
{"title":"Optimize Database Queries","description":"Implement user authentication feature","jobType":"REVIEW","jobState":"NEW","earnings":578.5,"companyId":"77","freelancerId":null},
{"title":"Write Unit Tests","description":"Optimize database queries for performance","jobType":"TEST","jobState":"NEW","earnings":637.3,"companyId":"51","freelancerId":null},
{"title":"Optimize Database Queries","description":"Write unit tests for new functionality","jobType":"TEST","jobState":"NEW","earnings":431.4,"companyId":"2","freelancerId":null},
{"title":"Write Unit Tests","description":"Optimize database queries for performance","jobType":"TEST","jobState":"NEW","earnings":523.9,"companyId":"29","freelancerId":null},
{"title":"Implement User Authentication","description":"Optimize database queries for performance","jobType":"IMPLEMENT","jobState":"NEW","earnings":348.0,"companyId":"46","freelancerId":null},
{"title":"Integrate Third-Party API","description":"Fix bug causing application crash","jobType":"OTHER","jobState":"NEW","earnings":519.0,"companyId":"78","freelancerId":null},
{"title":"Optimize Database Queries","description":"Refactor code to improve readability","jobType":"REVIEW","jobState":"NEW","earnings":963.8,"companyId":"34","freelancerId":null},
{"title":"Refactor Frontend Components","description":"Refactor code to improve readability","jobType":"TEST","jobState":"NEW","earnings":669.8,"companyId":"27","freelancerId":null},
{"title":"Write Unit Tests","description":"Optimize database queries for performance","jobType":"OTHER","jobState":"NEW","earnings":410.8,"companyId":"47","freelancerId":null},
{"title":"Refactor Frontend Components","description":"Fix bug causing application crash","jobType":"REVIEW","jobState":"NEW","earnings":597.2,"companyId":"84","freelancerId":null},
{"title":"Optimize Database Queries","description":"Optimize database queries for performance","jobType":"REVIEW","jobState":"NEW","earnings":462.0,"companyId":"19","freelancerId":null},
{"title":"Implement User Authentication","description":"Implement user authentication feature","jobType":"OTHER","jobState":"NEW","earnings":174.9,"companyId":"9","freelancerId":null},
{"title":"Integrate Third-Party API","description":"Implement user authentication feature","jobType":"REVIEW","jobState":"NEW","earnings":421.7,"companyId":"3","freelancerId":null},
{"title":"Write Unit Tests","description":"Write unit tests for new functionality","jobType":"TEST","jobState":"NEW","earnings":659.7,"companyId":"40","freelancerId":null},
{"title":"Implement User Authentication","description":"Optimize database queries for performance","jobType":"REVIEW","jobState":"NEW","earnings":519.9,"companyId":"68","freelancerId":null},
{"title":"Write Unit Tests","description":"Fix bug causing application crash","jobType":"REVIEW","jobState":"NEW","earnings":735.6,"companyId":"34","freelancerId":null},
{"title":"Refactor Frontend Components","description":"Refactor code to improve readability","jobType":"OTHER","jobState":"NEW","earnings":825.8,"companyId":"13","freelancerId":null},
{"title":"Optimize Database Queries","description":"Optimize database queries for performance","jobType":"TEST","jobState":"NEW","earnings":389.8,"companyId":"46","freelancerId":null},
{"title":"Write Unit Tests","description":"Refactor code to improve readability","jobType":"OTHER","jobState":"NEW","earnings":745.2,"companyId":"17","freelancerId":null},
{"title":"Optimize Database Queries","description":"Optimize database queries for performance","jobType":"TEST","jobState":"NEW","earnings":249.5,"companyId":"46","freelancerId":null},
{"title":"Integrate Third-Party API","description":"Write unit tests for new functionality","jobType":"OTHER","jobState":"NEW","earnings":537.8,"companyId":"33","freelancerId":null},
{"title":"Optimize Database Queries","description":"Optimize database queries for performance","jobType":"REVIEW","jobState":"NEW","earnings":560.3,"companyId":"75","freelancerId":null},
{"title":"Integrate Third-Party API","description":"Fix bug causing application crash","jobType":"IMPLEMENT","jobState":"NEW","earnings":538.2,"companyId":"21","freelancerId":null},
{"title":"Integrate Third-Party API","description":"Optimize database queries for performance","jobType":"REVIEW","jobState":"NEW","earnings":313.2,"companyId":"23","freelancerId":null},
{"title":"Optimize Database Queries","description":"Fix bug causing application crash","jobType":"TEST","jobState":"NEW","earnings":246.9,"companyId":"17","freelancerId":null},
{"title":"Refactor Frontend Components","description":"Implement user authentication feature","jobType":"OTHER","jobState":"NEW","earnings":493.8,"companyId":"23","freelancerId":null},
{"title":"Implement User Authentication","description":"Implement user authentication feature","jobType":"OTHER","jobState":"NEW","earnings":273.7,"companyId":"6","freelancerId":null},
{"title":"Write Unit Tests","description":"Refactor code to improve readability","jobType":"TEST","jobState":"NEW","earnings":922.7,"companyId":"21","freelancerId":null},
{"title":"Refactor Frontend Components","description":"Optimize database queries for performance","jobType":"OTHER","jobState":"NEW","earnings":454.5,"companyId":"4","freelancerId":null},
{"title":"Implement User Authentication","description":"Optimize database queries for performance","jobType":"OTHER","jobState":"NEW","earnings":489.3,"companyId":"31","freelancerId":null},
{"title":"Refactor Frontend Components","description":"Refactor code to improve readability","jobType":"TEST","jobState":"NEW","earnings":486.2,"companyId":"47","freelancerId":null},
{"title":"Optimize Database Queries","description":"Fix bug causing application crash","jobType":"IMPLEMENT","jobState":"NEW","earnings":267.4,"companyId":"17","freelancerId":null},
{"title":"Optimize Database Queries","description":"Optimize database queries for performance","jobType":"REVIEW","jobState":"NEW","earnings":889.0,"companyId":"25","freelancerId":null},
{"title":"Implement User Authentication","description":"Refactor code to improve readability","jobType":"OTHER","jobState":"NEW","earnings":390.1,"companyId":"64","freelancerId":null},
{"title":"Integrate Third-Party API","description":"Optimize database queries for performance","jobType":"OTHER","jobState":"NEW","earnings":190.7,"companyId":"47","freelancerId":null},
{"title":"Optimize Database Queries","description":"Fix bug causing application crash","jobType":"IMPLEMENT","jobState":"NEW","earnings":432.3,"companyId":"56","freelancerId":null},
{"title":"Write Unit Tests","description":"Fix bug causing application crash","jobType":"OTHER","jobState":"NEW","earnings":911.4,"companyId":"29","freelancerId":null},
{"title":"Integrate Third-Party API","description":"Refactor code to improve readability","jobType":"IMPLEMENT","jobState":"NEW","earnings":297.5,"companyId":"6","freelancerId":null},
{"title":"Refactor Frontend Components","description":"Implement user authentication feature","jobType":"OTHER","jobState":"NEW","earnings":276.2,"companyId":"1","freelancerId":null},
{"title":"Write Unit Tests","description":"Write unit tests for new functionality","jobType":"IMPLEMENT","jobState":"NEW","earnings":100.7,"companyId":"5","freelancerId":null},
{"title":"Integrate Third-Party API","description":"Write unit tests for new functionality","jobType":"TEST","jobState":"NEW","earnings":825.9,"companyId":"65","freelancerId":null},
{"title":"Implement User Authentication","description":"Fix bug causing application crash","jobType":"IMPLEMENT","jobState":"NEW","earnings":693.3,"companyId":"98","freelancerId":null},
{"title":"Write Unit Tests","description":"Optimize database queries for performance","jobType":"TEST","jobState":"NEW","earnings":373.2,"companyId":"28","freelancerId":null},
{"title":"Refactor Frontend Components","description":"Implement user authentication feature","jobType":"IMPLEMENT","jobState":"NEW","earnings":633.4,"companyId":"56","freelancerId":null},
{"title":"Refactor Frontend Components","description":"Fix bug causing application crash","jobType":"IMPLEMENT","jobState":"NEW","earnings":335.4,"companyId":"58","freelancerId":null},
{"title":"Implement User Authentication","description":"Write unit tests for new functionality","jobType":"TEST","jobState":"NEW","earnings":147.4,"companyId":"45","freelancerId":null},
{"title":"Refactor Frontend Components","description":"Implement user authentication feature","jobType":"IMPLEMENT","jobState":"NEW","earnings":856.7,"companyId":"41","freelancerId":null},
{"title":"Refactor Frontend Components","description":"Fix bug causing application crash","jobType":"REVIEW","jobState":"NEW","earnings":982.3,"companyId":"5","freelancerId":null},
{"title":"Optimize Database Queries","description":"Refactor code to improve readability","jobType":"REVIEW","jobState":"NEW","earnings":252.7,"companyId":"44","freelancerId":null},
{"title":"Implement User Authentication","description":"Fix bug causing application crash","jobType":"REVIEW","jobState":"NEW","earnings":122.2,"companyId":"36","freelancerId":null},
{"title":"Implement User Authentication","description":"Optimize database queries for performance","jobType":"REVIEW","jobState":"NEW","earnings":470.7,"companyId":"75","freelancerId":null},
{"title":"Optimize Database Queries","description":"Implement user authentication feature","jobType":"TEST","jobState":"NEW","earnings":560.4,"companyId":"45","freelancerId":null},
{"title":"Integrate Third-Party API","description":"Fix bug causing application crash","jobType":"IMPLEMENT","jobState":"NEW","earnings":149.8,"companyId":"70","freelancerId":null},
{"title":"Integrate Third-Party API","description":"Write unit tests for new functionality","jobType":"REVIEW","jobState":"NEW","earnings":234.3,"companyId":"33","freelancerId":null},
{"title":"Refactor Frontend Components","description":"Optimize database queries for performance","jobType":"REVIEW","jobState":"NEW","earnings":604.7,"companyId":"68","freelancerId":null},
{"title":"Refactor Frontend Components","description":"Optimize database queries for performance","jobType":"IMPLEMENT","jobState":"NEW","earnings":990.2,"companyId":"8","freelancerId":null},
{"title":"Refactor Frontend Components","description":"Refactor code to improve readability","jobType":"REVIEW","jobState":"NEW","earnings":665.2,"companyId":"4","freelancerId":null},
{"title":"Integrate Third-Party API","description":"Fix bug causing application crash","jobType":"OTHER","jobState":"NEW","earnings":382.3,"companyId":"77","freelancerId":null},
{"title":"Write Unit Tests","description":"Write unit tests for new functionality","jobType":"OTHER","jobState":"NEW","earnings":523.0,"companyId":"21","freelancerId":null},
{"title":"Optimize Database Queries","description":"Optimize database queries for performance","jobType":"IMPLEMENT","jobState":"NEW","earnings":797.9,"companyId":"64","freelancerId":null},
{"title":"Write Unit Tests","description":"Write unit tests for new functionality","jobType":"IMPLEMENT","jobState":"NEW","earnings":517.7,"companyId":"86","freelancerId":null},
{"title":"Optimize Database Queries","description":"Optimize database queries for performance","jobType":"TEST","jobState":"NEW","earnings":438.1,"companyId":"85","freelancerId":null},
{"title":"Integrate Third-Party API","description":"Optimize database queries for performance","jobType":"REVIEW","jobState":"NEW","earnings":155.3,"companyId":"73","freelancerId":null},
{"title":"Write Unit Tests","description":"Refactor code to improve readability","jobType":"OTHER","jobState":"NEW","earnings":767.5,"companyId":"35","freelancerId":null},
{"title":"Optimize Database Queries","description":"Fix bug causing application crash","jobType":"TEST","jobState":"NEW","earnings":140.2,"companyId":"49","freelancerId":null},
{"title":"Implement User Authentication","description":"Write unit tests for new functionality","jobType":"TEST","jobState":"NEW","earnings":818.9,"companyId":"70","freelancerId":null},
{"title":"Integrate Third-Party API","description":"Fix bug causing application crash","jobType":"REVIEW","jobState":"NEW","earnings":237.3,"companyId":"89","freelancerId":null},
{"title":"Write Unit Tests","description":"Write unit tests for new functionality","jobType":"OTHER","jobState":"NEW","earnings":914.7,"companyId":"97","freelancerId":null},
{"title":"Implement User Authentication","description":"Optimize database queries for performance","jobType":"OTHER","jobState":"NEW","earnings":467.1,"companyId":"57","freelancerId":null},
{"title":"Optimize Database Queries","description":"Optimize database queries for performance","jobType":"OTHER","jobState":"NEW","earnings":756.2,"companyId":"64","freelancerId":null},
{"title":"Optimize Database Queries","description":"Fix bug causing application crash","jobType":"IMPLEMENT","jobState":"NEW","earnings":883.8,"companyId":"21","freelancerId":null},
{"title":"Write Unit Tests","description":"Fix bug causing application crash","jobType":"OTHER","jobState":"NEW","earnings":490.6,"companyId":"52","freelancerId":null},
{"title":"Write Unit Tests","description":"Fix bug causing application crash","jobType":"REVIEW","jobState":"NEW","earnings":485.8,"companyId":"19","freelancerId":null},
{"title":"Implement User Authentication","description":"Implement user authentication feature","jobType":"REVIEW","jobState":"NEW","earnings":509.4,"companyId":"54","freelancerId":null},
{"title":"Refactor Frontend Components","description":"Fix bug causing application crash","jobType":"IMPLEMENT","jobState":"NEW","earnings":386.0,"companyId":"74","freelancerId":null},
{"title":"Optimize Database Queries","description":"Refactor code to improve readability","jobType":"TEST","jobState":"NEW","earnings":257.1,"companyId":"40","freelancerId":null},
{"title":"Write Unit Tests","description":"Implement user authentication feature","jobType":"TEST","jobState":"NEW","earnings":543.2,"companyId":"25","freelancerId":null},
{"title":"Optimize Database Queries","description":"Write unit tests for new functionality","jobType":"TEST","jobState":"NEW","earnings":602.1,"companyId":"91","freelancerId":null},
{"title":"Refactor Frontend Components","description":"Write unit tests for new functionality","jobType":"OTHER","jobState":"NEW","earnings":547.0,"companyId":"6","freelancerId":null},
{"title":"Refactor Frontend Components","description":"Write unit tests for new functionality","jobType":"REVIEW","jobState":"NEW","earnings":605.2,"companyId":"45","freelancerId":null},
{"title":"Integrate Third-Party API","description":"Implement user authentication feature","jobType":"TEST","jobState":"NEW","earnings":379.1,"companyId":"33","freelancerId":null},
{"title":"Refactor Frontend Components","description":"Refactor code to improve readability","jobType":"TEST","jobState":"NEW","earnings":161.4,"companyId":"25","freelancerId":null},
{"title":"Implement User Authentication","description":"Implement user authentication feature","jobType":"OTHER","jobState":"NEW","earnings":692.8,"companyId":"91","freelancerId":null},
{"title":"Implement User Authentication","description":"Write unit tests for new functionality","jobType":"IMPLEMENT","jobState":"NEW","earnings":622.7,"companyId":"62","freelancerId":null},
{"title":"Write Unit Tests","description":"Refactor code to improve readability","jobType":"IMPLEMENT","jobState":"NEW","earnings":791.1,"companyId":"84","freelancerId":null},
{"title":"Optimize Database Queries","description":"Implement user authentication feature","jobType":"TEST","jobState":"NEW","earnings":863.7,"companyId":"33","freelancerId":null},
{"title":"Optimize Database Queries","description":"Implement user authentication feature","jobType":"OTHER","jobState":"NEW","earnings":250.6,"companyId":"71","freelancerId":null},
{"title":"Optimize Database Queries","description":"Implement user authentication feature","jobType":"TEST","jobState":"NEW","earnings":735.8,"companyId":"63","freelancerId":null},
{"title":"Refactor Frontend Components","description":"Fix bug causing application crash","jobType":"OTHER","jobState":"NEW","earnings":962.9,"companyId":"79","freelancerId":null},
{"title":"Write Unit Tests","description":"Write unit tests for new functionality","jobType":"TEST","jobState":"NEW","earnings":206.3,"companyId":"25","freelancerId":null},
{"title":"Optimize Database Queries","description":"Optimize database queries for performance","jobType":"TEST","jobState":"NEW","earnings":340.5,"companyId":"65","freelancerId":null},
{"title":"Implement User Authentication","description":"Refactor code to improve readability","jobType":"OTHER","jobState":"NEW","earnings":668.0,"companyId":"54","freelancerId":null},
{"title":"Optimize Database Queries","description":"Refactor code to improve readability","jobType":"REVIEW","jobState":"NEW","earnings":841.1,"companyId":"24","freelancerId":null},
{"title":"Implement User Authentication","description":"Write unit tests for new functionality","jobType":"TEST","jobState":"NEW","earnings":536.4,"companyId":"38","freelancerId":null},
{"title":"Implement User Authentication","description":"Optimize database queries for performance","jobType":"OTHER","jobState":"NEW","earnings":931.2,"companyId":"12","freelancerId":null},
{"title":"Implement User Authentication","description":"Write unit tests for new functionality","jobType":"REVIEW","jobState":"NEW","earnings":477.3,"companyId":"21","freelancerId":null},
{"title":"Implement User Authentication","description":"Write unit tests for new functionality","jobType":"REVIEW","jobState":"NEW","earnings":879.9,"companyId":"40","freelancerId":null},
{"title":"Optimize Database Queries","description":"Fix bug causing application crash","jobType":"REVIEW","jobState":"NEW","earnings":161.9,"companyId":"59","freelancerId":null},
{"title":"Integrate Third-Party API","description":"Optimize database queries for performance","jobType":"REVIEW","jobState":"NEW","earnings":370.2,"companyId":"95","freelancerId":null},
{"title":"Write Unit Tests","description":"Write unit tests for new functionality","jobType":"IMPLEMENT","jobState":"NEW","earnings":238.2,"companyId":"54","freelancerId":null},
{"title":"Write Unit Tests","description":"Optimize database queries for performance","jobType":"IMPLEMENT","jobState":"NEW","earnings":212.2,"companyId":"35","freelancerId":null},
{"title":"Integrate Third-Party API","description":"Implement user authentication feature","jobType":"REVIEW","jobState":"NEW","earnings":642.4,"companyId":"22","freelancerId":null},
{"title":"Integrate Third-Party API","description":"Implement user authentication feature","jobType":"IMPLEMENT","jobState":"NEW","earnings":795.3,"companyId":"90","freelancerId":null},
{"title":"Refactor Frontend Components","description":"Fix bug causing application crash","jobType":"OTHER","jobState":"NEW","earnings":327.2,"companyId":"47","freelancerId":null},
{"title":"Integrate Third-Party API","description":"Implement user authentication feature","jobType":"TEST","jobState":"NEW","earnings":867.6,"companyId":"98","freelancerId":null},
{"title":"Implement User Authentication","description":"Refactor code to improve readability","jobType":"OTHER","jobState":"NEW","earnings":228.6,"companyId":"34","freelancerId":null},
{"title":"Optimize Database Queries","description":"Refactor code to improve readability","jobType":"OTHER","jobState":"NEW","earnings":858.3,"companyId":"51","freelancerId":null},
{"title":"Implement User Authentication","description":"Refactor code to improve readability","jobType":"IMPLEMENT","jobState":"NEW","earnings":755.5,"companyId":"19","freelancerId":null},
{"title":"Optimize Database Queries","description":"Refactor code to improve readability","jobType":"IMPLEMENT","jobState":"NEW","earnings":765.7,"companyId":"18","freelancerId":null},
{"title":"Integrate Third-Party API","description":"Write unit tests for new functionality","jobType":"TEST","jobState":"NEW","earnings":269.7,"companyId":"68","freelancerId":null},
{"title":"Implement User Authentication","description":"Fix bug causing application crash","jobType":"IMPLEMENT","jobState":"NEW","earnings":165.6,"companyId":"86","freelancerId":null},
{"title":"Refactor Frontend Components","description":"Refactor code to improve readability","jobType":"TEST","jobState":"NEW","earnings":391.9,"companyId":"76","freelancerId":null},
{"title":"Implement User Authentication","description":"Optimize database queries for performance","jobType":"OTHER","jobState":"NEW","earnings":176.9,"companyId":"50","freelancerId":null},
{"title":"Implement User Authentication","description":"Optimize database queries for performance","jobType":"IMPLEMENT","jobState":"NEW","earnings":927.1,"companyId":"65","freelancerId":null},
{"title":"Write Unit Tests","description":"Implement user authentication feature","jobType":"REVIEW","jobState":"NEW","earnings":842.4,"companyId":"14","freelancerId":null},
{"title":"Implement User Authentication","description":"Fix bug causing application crash","jobType":"OTHER","jobState":"NEW","earnings":265.4,"companyId":"16","freelancerId":null},
{"title":"Optimize Database Queries","description":"Write unit tests for new functionality","jobType":"TEST","jobState":"NEW","earnings":792.0,"companyId":"27","freelancerId":null},
{"title":"Write Unit Tests","description":"Write unit tests for new functionality","jobType":"OTHER","jobState":"NEW","earnings":671.9,"companyId":"75","freelancerId":null},
{"title":"Implement User Authentication","description":"Refactor code to improve readability","jobType":"REVIEW","jobState":"NEW","earnings":212.5,"companyId":"75","freelancerId":null},
{"title":"Integrate Third-Party API","description":"Refactor code to improve readability","jobType":"IMPLEMENT","jobState":"NEW","earnings":687.5,"companyId":"87","freelancerId":null},
{"title":"Optimize Database Queries","description":"Refactor code to improve readability","jobType":"TEST","jobState":"NEW","earnings":976.0,"companyId":"97","freelancerId":null},
{"title":"Write Unit Tests","description":"Fix bug causing application crash","jobType":"REVIEW","jobState":"NEW","earnings":784.9,"companyId":"40","freelancerId":null},
{"title":"Refactor Frontend Components","description":"Write unit tests for new functionality","jobType":"TEST","jobState":"NEW","earnings":708.1,"companyId":"5","freelancerId":null},
{"title":"Optimize Database Queries","description":"Optimize database queries for performance","jobType":"IMPLEMENT","jobState":"NEW","earnings":286.6,"companyId":"31","freelancerId":null},
{"title":"Refactor Frontend Components","description":"Refactor code to improve readability","jobType":"REVIEW","jobState":"NEW","earnings":481.6,"companyId":"79","freelancerId":null},
{"title":"Optimize Database Queries","description":"Optimize database queries for performance","jobType":"REVIEW","jobState":"NEW","earnings":850.9,"companyId":"82","freelancerId":null},
{"title":"Optimize Database Queries","description":"Fix bug causing application crash","jobType":"OTHER","jobState":"NEW","earnings":642.6,"companyId":"42","freelancerId":null},
{"title":"Integrate Third-Party API","description":"Implement user authentication feature","jobType":"TEST","jobState":"NEW","earnings":542.3,"companyId":"100","freelancerId":null},
{"title":"Write Unit Tests","description":"Optimize database queries for performance","jobType":"REVIEW","jobState":"NEW","earnings":452.5,"companyId":"56","freelancerId":null},
{"title":"Integrate Third-Party API","description":"Fix bug causing application crash","jobType":"IMPLEMENT","jobState":"NEW","earnings":910.0,"companyId":"21","freelancerId":null},
{"title":"Integrate Third-Party API","description":"Implement user authentication feature","jobType":"TEST","jobState":"NEW","earnings":659.5,"companyId":"29","freelancerId":null},
{"title":"Optimize Database Queries","description":"Implement user authentication feature","jobType":"OTHER","jobState":"NEW","earnings":746.6,"companyId":"63","freelancerId":null},
{"title":"Optimize Database Queries","description":"Implement user authentication feature","jobType":"TEST","jobState":"NEW","earnings":786.9,"companyId":"60","freelancerId":null},
{"title":"Refactor Frontend Components","description":"Refactor code to improve readability","jobType":"TEST","jobState":"NEW","earnings":444.5,"companyId":"11","freelancerId":null},
{"title":"Integrate Third-Party API","description":"Optimize database queries for performance","jobType":"OTHER","jobState":"NEW","earnings":567.2,"companyId":"93","freelancerId":null},
{"title":"Integrate Third-Party API","description":"Fix bug causing application crash","jobType":"TEST","jobState":"NEW","earnings":215.4,"companyId":"59","freelancerId":null},
{"title":"Implement User Authentication","description":"Write unit tests for new functionality","jobType":"IMPLEMENT","jobState":"NEW","earnings":603.2,"companyId":"7","freelancerId":null},
{"title":"Write Unit Tests","description":"Refactor code to improve readability","jobType":"IMPLEMENT","jobState":"NEW","earnings":116.7,"companyId":"69","freelancerId":null},
{"title":"Optimize Database Queries","description":"Optimize database queries for performance","jobType":"REVIEW","jobState":"NEW","earnings":297.9,"companyId":"7","freelancerId":null},
{"title":"Integrate Third-Party API","description":"Write unit tests for new functionality","jobType":"IMPLEMENT","jobState":"NEW","earnings":526.4,"companyId":"93","freelancerId":null},
{"title":"Integrate Third-Party API","description":"Optimize database queries for performance","jobType":"REVIEW","jobState":"NEW","earnings":650.2,"companyId":"99","freelancerId":null},
{"title":"Refactor Frontend Components","description":"Fix bug causing application crash","jobType":"TEST","jobState":"NEW","earnings":949.2,"companyId":"3","freelancerId":null},
{"title":"Write Unit Tests","description":"Write unit tests for new functionality","jobType":"IMPLEMENT","jobState":"NEW","earnings":357.6,"companyId":"69","freelancerId":null},
{"title":"Refactor Frontend Components","description":"Refactor code to improve readability","jobType":"OTHER","jobState":"NEW","earnings":452.0,"companyId":"96","freelancerId":null},
{"title":"Integrate Third-Party API","description":"Fix bug causing application crash","jobType":"IMPLEMENT","jobState":"NEW","earnings":319.3,"companyId":"86","freelancerId":null},
{"title":"Implement User Authentication","description":"Refactor code to improve readability","jobType":"OTHER","jobState":"NEW","earnings":883.3,"companyId":"92","freelancerId":null},
{"title":"Integrate Third-Party API","description":"Fix bug causing application crash","jobType":"OTHER","jobState":"NEW","earnings":941.5,"companyId":"32","freelancerId":null},
{"title":"Write Unit Tests","description":"Fix bug causing application crash","jobType":"TEST","jobState":"NEW","earnings":606.6,"companyId":"87","freelancerId":null},
{"title":"Integrate Third-Party API","description":"Optimize database queries for performance","jobType":"REVIEW","jobState":"NEW","earnings":930.1,"companyId":"24","freelancerId":null},
{"title":"Write Unit Tests","description":"Optimize database queries for performance","jobType":"IMPLEMENT","jobState":"NEW","earnings":667.6,"companyId":"28","freelancerId":null},
{"title":"Write Unit Tests","description":"Refactor code to improve readability","jobType":"IMPLEMENT","jobState":"NEW","earnings":143.9,"companyId":"34","freelancerId":null},
{"title":"Write Unit Tests","description":"Optimize database queries for performance","jobType":"OTHER","jobState":"NEW","earnings":581.0,"companyId":"23","freelancerId":null},
{"title":"Implement User Authentication","description":"Refactor code to improve readability","jobType":"REVIEW","jobState":"NEW","earnings":364.5,"companyId":"17","freelancerId":null},
{"title":"Write Unit Tests","description":"Fix bug causing application crash","jobType":"TEST","jobState":"NEW","earnings":472.2,"companyId":"62","freelancerId":null},
{"title":"Integrate Third-Party API","description":"Refactor code to improve readability","jobType":"OTHER","jobState":"NEW","earnings":283.1,"companyId":"77","freelancerId":null},
{"title":"Refactor Frontend Components","description":"Write unit tests for new functionality","jobType":"REVIEW","jobState":"NEW","earnings":598.5,"companyId":"100","freelancerId":null},
{"title":"Implement User Authentication","description":"Fix bug causing application crash","jobType":"IMPLEMENT","jobState":"NEW","earnings":714.2,"companyId":"72","freelancerId":null},
{"title":"Optimize Database Queries","description":"Fix bug causing application crash","jobType":"TEST","jobState":"NEW","earnings":726.2,"companyId":"14","freelancerId":null},
{"title":"Refactor Frontend Components","description":"Implement user authentication feature","jobType":"TEST","jobState":"NEW","earnings":411.3,"companyId":"86","freelancerId":null},
{"title":"Integrate Third-Party API","description":"Refactor code to improve readability","jobType":"OTHER","jobState":"NEW","earnings":633.3,"companyId":"10","freelancerId":null},
{"title":"Refactor Frontend Components","description":"Write unit tests for new functionality","jobType":"IMPLEMENT","jobState":"NEW","earnings":230.2,"companyId":"89","freelancerId":null},
{"title":"Write Unit Tests","description":"Write unit tests for new functionality","jobType":"OTHER","jobState":"NEW","earnings":880.1,"companyId":"56","freelancerId":null},
{"title":"Refactor Frontend Components","description":"Write unit tests for new functionality","jobType":"OTHER","jobState":"NEW","earnings":205.8,"companyId":"31","freelancerId":null},
{"title":"Integrate Third-Party API","description":"Fix bug causing application crash","jobType":"OTHER","jobState":"NEW","earnings":892.5,"companyId":"18","freelancerId":null},
{"title":"Write Unit Tests","description":"Write unit tests for new functionality","jobType":"IMPLEMENT","jobState":"NEW","earnings":746.9,"companyId":"61","freelancerId":null},
{"title":"Write Unit Tests","description":"Refactor code to improve readability","jobType":"OTHER","jobState":"NEW","earnings":264.1,"companyId":"97","freelancerId":null},
{"title":"Refactor Frontend Components","description":"Optimize database queries for performance","jobType":"TEST","jobState":"NEW","earnings":924.2,"companyId":"64","freelancerId":null},
{"title":"Integrate Third-Party API","description":"Refactor code to improve readability","jobType":"TEST","jobState":"NEW","earnings":194.6,"companyId":"66","freelancerId":null},
{"title":"Integrate Third-Party API","description":"Write unit tests for new functionality","jobType":"OTHER","jobState":"NEW","earnings":453.8,"companyId":"65","freelancerId":null},
{"title":"Optimize Database Queries","description":"Write unit tests for new functionality","jobType":"TEST","jobState":"NEW","earnings":368.3,"companyId":"75","freelancerId":null},
{"title":"Implement User Authentication","description":"Implement user authentication feature","jobType":"REVIEW","jobState":"NEW","earnings":357.6,"companyId":"4","freelancerId":null},
{"title":"Integrate Third-Party API","description":"Fix bug causing application crash","jobType":"TEST","jobState":"NEW","earnings":605.6,"companyId":"8","freelancerId":null},
{"title":"Integrate Third-Party API","description":"Refactor code to improve readability","jobType":"REVIEW","jobState":"NEW","earnings":897.6,"companyId":"22","freelancerId":null},
{"title":"Write Unit Tests","description":"Refactor code to improve readability","jobType":"IMPLEMENT","jobState":"NEW","earnings":696.0,"companyId":"93","freelancerId":null},
{"title":"Refactor Frontend Components","description":"Write unit tests for new functionality","jobType":"IMPLEMENT","jobState":"NEW","earnings":247.0,"companyId":"9","freelancerId":null},
{"title":"Write Unit Tests","description":"Implement user authentication feature","jobType":"REVIEW","jobState":"NEW","earnings":968.8,"companyId":"85","freelancerId":null},
{"title":"Integrate Third-Party API","description":"Implement user authentication feature","jobType":"TEST","jobState":"NEW","earnings":759.0,"companyId":"26","freelancerId":null},
{"title":"Implement User Authentication","description":"Optimize database queries for performance","jobType":"OTHER","jobState":"NEW","earnings":798.1,"companyId":"72","freelancerId":null},
{"title":"Write Unit Tests","description":"Refactor code to improve readability","jobType":"TEST","jobState":"NEW","earnings":921.0,"companyId":"29","freelancerId":null},
{"title":"Write Unit Tests","description":"Implement user authentication feature","jobType":"TEST","jobState":"NEW","earnings":188.9,"companyId":"17","freelancerId":null},
{"title":"Write Unit Tests","description":"Optimize database queries for performance","jobType":"REVIEW","jobState":"NEW","earnings":511.3,"companyId":"82","freelancerId":null},
{"title":"Integrate Third-Party API","description":"Refactor code to improve readability","jobType":"IMPLEMENT","jobState":"NEW","earnings":822.8,"companyId":"46","freelancerId":null},
{"title":"Refactor Frontend Components","description":"Fix bug causing application crash","jobType":"REVIEW","jobState":"NEW","earnings":953.9,"companyId":"54","freelancerId":null},
{"title":"Integrate Third-Party API","description":"Fix bug causing application crash","jobType":"REVIEW","jobState":"NEW","earnings":118.0,"companyId":"32","freelancerId":null},
{"title":"Integrate Third-Party API","description":"Fix bug causing application crash","jobType":"OTHER","jobState":"NEW","earnings":256.1,"companyId":"26","freelancerId":null},
{"title":"Refactor Frontend Components","description":"Write unit tests for new functionality","jobType":"REVIEW","jobState":"NEW","earnings":771.4,"companyId":"13","freelancerId":null},
{"title":"Refactor Frontend Components","description":"Optimize database queries for performance","jobType":"TEST","jobState":"NEW","earnings":139.8,"companyId":"48","freelancerId":null},
{"title":"Implement User Authentication","description":"Implement user authentication feature","jobType":"REVIEW","jobState":"NEW","earnings":898.2,"companyId":"51","freelancerId":null},
{"title":"Write Unit Tests","description":"Refactor code to improve readability","jobType":"TEST","jobState":"NEW","earnings":235.3,"companyId":"43","freelancerId":null},
{"title":"Integrate Third-Party API","description":"Write unit tests for new functionality","jobType":"OTHER","jobState":"NEW","earnings":231.8,"companyId":"90","freelancerId":null},
{"title":"Implement User Authentication","description":"Write unit tests for new functionality","jobType":"TEST","jobState":"NEW","earnings":551.0,"companyId":"11","freelancerId":null},
{"title":"Integrate Third-Party API","description":"Write unit tests for new functionality","jobType":"TEST","jobState":"NEW","earnings":317.9,"companyId":"49","freelancerId":null},
{"title":"Integrate Third-Party API","description":"Implement user authentication feature","jobType":"OTHER","jobState":"NEW","earnings":307.9,"companyId":"16","freelancerId":null},
{"title":"Implement User Authentication","description":"Write unit tests for new functionality","jobType":"OTHER","jobState":"NEW","earnings":159.6,"companyId":"65","freelancerId":null},
{"title":"Refactor Frontend Components","description":"Refactor code to improve readability","jobType":"OTHER","jobState":"NEW","earnings":995.4,"companyId":"56","freelancerId":null},
{"title":"Refactor Frontend Components","description":"Refactor code to improve readability","jobType":"OTHER","jobState":"NEW","earnings":707.3,"companyId":"81","freelancerId":null},
{"title":"Refactor Frontend Components","description":"Optimize database queries for performance","jobType":"IMPLEMENT","jobState":"NEW","earnings":581.3,"companyId":"47","freelancerId":null},
{"title":"Optimize Database Queries","description":"Refactor code to improve readability","jobType":"IMPLEMENT","jobState":"NEW","earnings":924.1,"companyId":"22","freelancerId":null},
{"title":"Refactor Frontend Components","description":"Optimize database queries for performance","jobType":"REVIEW","jobState":"NEW","earnings":996.9,"companyId":"22","freelancerId":null},
{"title":"Optimize Database Queries","description":"Implement user authentication feature","jobType":"IMPLEMENT","jobState":"NEW","earnings":644.1,"companyId":"15","freelancerId":null},
{"title":"Write Unit Tests","description":"Fix bug causing application crash","jobType":"REVIEW","jobState":"NEW","earnings":402.8,"companyId":"83","freelancerId":null},
{"title":"Optimize Database Queries","description":"Optimize database queries for performance","jobType":"OTHER","jobState":"NEW","earnings":694.9,"companyId":"21","freelancerId":null},
{"title":"Integrate Third-Party API","description":"Optimize database queries for performance","jobType":"REVIEW","jobState":"NEW","earnings":765.1,"companyId":"14","freelancerId":null}]